inkwell/__init__.py
inkwell/cli.py
inkwell/audio/__init__.py
inkwell/audio/downloader.py
inkwell/config/__init__.py
inkwell/config/crypto.py
inkwell/config/defaults.py
inkwell/config/logging.py
inkwell/config/manager.py
inkwell/config/precedence.py
inkwell/config/schema.py
inkwell/extraction/__init__.py
inkwell/extraction/cache.py
inkwell/extraction/engine.py
inkwell/extraction/models.py
inkwell/extraction/template_selector.py
inkwell/extraction/templates.py
inkwell/extraction/extractors/__init__.py
inkwell/extraction/extractors/base.py
inkwell/extraction/extractors/claude.py
inkwell/extraction/extractors/gemini.py
inkwell/feeds/__init__.py
inkwell/feeds/models.py
inkwell/feeds/parser.py
inkwell/feeds/validator.py
inkwell/interview/__init__.py
inkwell/interview/simple_interviewer.py
inkwell/output/__init__.py
inkwell/output/manager.py
inkwell/output/markdown.py
inkwell/output/models.py
inkwell/pipeline/__init__.py
inkwell/pipeline/models.py
inkwell/pipeline/orchestrator.py
inkwell/templates/categories/interview/books-mentioned.yaml
inkwell/templates/categories/tech/tools-mentioned.yaml
inkwell/templates/default/key-concepts.yaml
inkwell/templates/default/quotes.yaml
inkwell/templates/default/summary.yaml
inkwell/transcription/__init__.py
inkwell/transcription/cache.py
inkwell/transcription/gemini.py
inkwell/transcription/manager.py
inkwell/transcription/models.py
inkwell/transcription/youtube.py
inkwell/utils/__init__.py
inkwell/utils/api_keys.py
inkwell/utils/cache.py
inkwell/utils/costs.py
inkwell/utils/datetime.py
inkwell/utils/display.py
inkwell/utils/errors.py
inkwell/utils/json_utils.py
inkwell/utils/logging.py
inkwell/utils/paths.py
inkwell/utils/progress.py
inkwell/utils/rate_limiter.py
inkwell/utils/retry.py
inkwell_cli-0.14.0.dist-info/licenses/LICENSE
inkwell_cli-0.14.0.dist-info/METADATA
inkwell_cli-0.14.0.dist-info/WHEEL
inkwell_cli-0.14.0.dist-info/entry_points.txt
inkwell_cli-0.14.0.dist-info/top_level.txt
inkwell_cli-0.14.0.dist-info/RECORD
