Metadata-Version: 2.4
Name: inkwell-cli
Version: 0.14.0
Summary: Transform podcast episodes into structured markdown notes
Author-email: Sergio Sanchez <chekos@users.noreply.github.com>
License: MIT
Project-URL: Homepage, https://github.com/chekos/inkwell-cli
Project-URL: Documentation, https://github.com/chekos/inkwell-cli#readme
Project-URL: Repository, https://github.com/chekos/inkwell-cli.git
Project-URL: Issues, https://github.com/chekos/inkwell-cli/issues
Project-URL: Changelog, https://github.com/chekos/inkwell-cli/releases
Keywords: podcast,transcription,markdown,notes,obsidian,cli,ai,llm
Classifier: Development Status :: 4 - Beta
Classifier: Intended Audience :: Developers
Classifier: Intended Audience :: End Users/Desktop
Classifier: License :: OSI Approved :: MIT License
Classifier: Programming Language :: Python :: 3
Classifier: Programming Language :: Python :: 3.10
Classifier: Programming Language :: Python :: 3.11
Classifier: Programming Language :: Python :: 3.12
Classifier: Topic :: Multimedia :: Sound/Audio
Classifier: Topic :: Text Processing :: Markup :: Markdown
Requires-Python: >=3.10
License-File: LICENSE
Requires-Dist: typer>=0.15.0
Requires-Dist: rich>=14.0.0
Requires-Dist: pyyaml>=6.0.2
Requires-Dist: feedparser>=6.0.11
Requires-Dist: pydantic>=2.10.0
Requires-Dist: pydantic-settings>=2.10.0
Requires-Dist: cryptography>=44.0.0
Requires-Dist: httpx>=0.28.0
Requires-Dist: platformdirs>=4.3.0
Requires-Dist: youtube-transcript-api>=1.0.0
Requires-Dist: yt-dlp>=2025.1.0
Requires-Dist: google-genai>=1.0.0
Requires-Dist: anthropic>=0.72.0
Requires-Dist: tenacity>=9.0.0
Requires-Dist: regex>=2024.11.0
Requires-Dist: aiofiles>=24.1.0
Requires-Dist: jinja2>=3.1.0
Provides-Extra: dev
Requires-Dist: pytest>=8.0.0; extra == "dev"
Requires-Dist: pytest-cov>=4.1.0; extra == "dev"
Requires-Dist: pytest-mock>=3.12.0; extra == "dev"
Requires-Dist: pytest-asyncio>=0.23.0; extra == "dev"
Requires-Dist: ruff>=0.3.0; extra == "dev"
Requires-Dist: mypy>=1.8.0; extra == "dev"
Requires-Dist: pre-commit>=3.6.0; extra == "dev"
Requires-Dist: types-pyyaml; extra == "dev"
Requires-Dist: respx>=0.20.0; extra == "dev"
Dynamic: license-file
